[
  {
    "_row_key": 1,
    "_row_size": 17,
    "id": 1,
    "editor_name": "购买月卡后立刻赠送",
    "reward_id": 20001,
    "monthly_pass_reward_type": 1
  },
  {
    "_row_key": 2,
    "_row_size": 17,
    "id": 2,
    "editor_name": "每日登录固定赠送",
    "reward_id": 20002,
    "monthly_pass_reward_type": 2
  },
  {
    "_row_key": 3,
    "_row_size": 17,
    "id": 3,
    "editor_name": "星光值获取效率增加",
    "monthly_pass_reward_type": 5,
    "param": 13000
  },
  {
    "_row_key": 4,
    "_row_size": 21,
    "id": 4,
    "editor_name": "废弃",
    "reward_id": 20004,
    "monthly_pass_reward_type": 3,
    "param": 5
  },
  {
    "_row_key": 5,
    "_row_size": 21,
    "id": 5,
    "editor_name": "废弃",
    "reward_id": 20004,
    "monthly_pass_reward_type": 3,
    "param": 10
  },
  {
    "_row_key": 6,
    "_row_size": 21,
    "id": 6,
    "editor_name": "废弃",
    "reward_id": 20003,
    "monthly_pass_reward_type": 3,
    "param": 15
  },
  {
    "_row_key": 7,
    "_row_size": 21,
    "id": 7,
    "editor_name": "废弃",
    "reward_id": 20004,
    "monthly_pass_reward_type": 3,
    "param": 20
  },
  {
    "_row_key": 8,
    "_row_size": 21,
    "id": 8,
    "editor_name": "废弃",
    "reward_id": 20004,
    "monthly_pass_reward_type": 3,
    "param": 25
  },
  {
    "_row_key": 9,
    "_row_size": 21,
    "id": 9,
    "editor_name": "废弃",
    "reward_id": 20004,
    "monthly_pass_reward_type": 3,
    "param": 30
  },
  {
    "_row_key": 10,
    "_row_size": 17,
    "id": 10,
    "editor_name": "废弃",
    "reward_id": 20005,
    "monthly_pass_reward_type": 4
  },
  {
    "_row_key": 11,
    "_row_size": 17,
    "id": 11,
    "editor_name": "废弃",
    "reward_id": 20006,
    "monthly_pass_reward_type": 4
  },
  {
    "_row_key": 12,
    "_row_size": 17,
    "id": 12,
    "editor_name": "废弃",
    "reward_id": 20007,
    "monthly_pass_reward_type": 4
  }
]