[
  {
    "_row_key": 1,
    "_row_size": 17,
    "id": 3004,
    "pet_type": 1,
    "expand_pet": [],
    "level": 60
  },
  {
    "_row_key": 2,
    "_row_size": 17,
    "id": 3005,
    "pet_type": 2,
    "expand_pet": [],
    "level": 60
  },
  {
    "_row_key": 3,
    "_row_size": 17,
    "id": 3006,
    "pet_type": 1,
    "expand_pet": [],
    "level": 60
  },
  {
    "_row_key": 4,
    "_row_size": 17,
    "id": 3007,
    "pet_type": 1,
    "expand_pet": [],
    "level": 60
  },
  {
    "_row_key": 5,
    "_row_size": 17,
    "id": 3011,
    "pet_type": 1,
    "expand_pet": [],
    "level": 60
  },
  {
    "_row_key": 6,
    "_row_size": 17,
    "id": 3012,
    "pet_type": 1,
    "expand_pet": [],
    "level": 60
  },
  {
    "_row_key": 7,
    "_row_size": 17,
    "id": 3013,
    "pet_type": 1,
    "expand_pet": [],
    "level": 60
  },
  {
    "_row_key": 8,
    "_row_size": 17,
    "id": 3016,
    "pet_type": 1,
    "expand_pet": [],
    "level": 60
  },
  {
    "_row_key": 9,
    "_row_size": 17,
    "id": 3019,
    "pet_type": 1,
    "expand_pet": [],
    "level": 60
  },
  {
    "_row_key": 10,
    "_row_size": 17,
    "id": 3022,
    "pet_type": 1,
    "expand_pet": [],
    "level": 60
  },
  {
    "_row_key": 11,
    "_row_size": 17,
    "id": 3027,
    "pet_type": 1,
    "expand_pet": [],
    "level": 60
  },
  {
    "_row_key": 12,
    "_row_size": 17,
    "id": 3031,
    "pet_type": 1,
    "expand_pet": [],
    "level": 60
  },
  {
    "_row_key": 13,
    "_row_size": 17,
    "id": 3035,
    "pet_type": 1,
    "expand_pet": [],
    "level": 60
  },
  {
    "_row_key": 14,
    "_row_size": 17,
    "id": 3036,
    "pet_type": 2,
    "expand_pet": [],
    "level": 60
  },
  {
    "_row_key": 15,
    "_row_size": 17,
    "id": 3037,
    "pet_type": 1,
    "expand_pet": [],
    "level": 60
  },
  {
    "_row_key": 16,
    "_row_size": 17,
    "id": 3039,
    "pet_type": 1,
    "expand_pet": [],
    "level": 60
  },
  {
    "_row_key": 17,
    "_row_size": 17,
    "id": 3042,
    "pet_type": 1,
    "expand_pet": [],
    "level": 60
  },
  {
    "_row_key": 18,
    "_row_size": 17,
    "id": 3044,
    "pet_type": 1,
    "expand_pet": [],
    "level": 60
  },
  {
    "_row_key": 19,
    "_row_size": 17,
    "id": 3047,
    "pet_type": 1,
    "expand_pet": [],
    "level": 60
  },
  {
    "_row_key": 20,
    "_row_size": 17,
    "id": 3050,
    "pet_type": 1,
    "expand_pet": [],
    "level": 60
  },
  {
    "_row_key": 21,
    "_row_size": 17,
    "id": 3057,
    "pet_type": 2,
    "expand_pet": [],
    "level": 60
  },
  {
    "_row_key": 22,
    "_row_size": 17,
    "id": 3063,
    "pet_type": 2,
    "expand_pet": [],
    "level": 60
  },
  {
    "_row_key": 23,
    "_row_size": 17,
    "id": 3064,
    "pet_type": 1,
    "expand_pet": [],
    "level": 60
  },
  {
    "_row_key": 24,
    "_row_size": 17,
    "id": 3066,
    "pet_type": 1,
    "expand_pet": [],
    "level": 60
  },
  {
    "_row_key": 25,
    "_row_size": 17,
    "id": 3067,
    "pet_type": 1,
    "expand_pet": [],
    "level": 60
  },
  {
    "_row_key": 26,
    "_row_size": 17,
    "id": 3069,
    "pet_type": 1,
    "expand_pet": [],
    "level": 60
  },
  {
    "_row_key": 27,
    "_row_size": 17,
    "id": 3071,
    "pet_type": 1,
    "expand_pet": [],
    "level": 60
  },
  {
    "_row_key": 28,
    "_row_size": 17,
    "id": 3074,
    "pet_type": 2,
    "expand_pet": [],
    "level": 60
  },
  {
    "_row_key": 29,
    "_row_size": 17,
    "id": 3077,
    "pet_type": 1,
    "expand_pet": [],
    "level": 60
  },
  {
    "_row_key": 30,
    "_row_size": 17,
    "id": 3088,
    "pet_type": 1,
    "expand_pet": [],
    "level": 60
  },
  {
    "_row_key": 31,
    "_row_size": 17,
    "id": 3089,
    "pet_type": 1,
    "expand_pet": [],
    "level": 60
  },
  {
    "_row_key": 32,
    "_row_size": 17,
    "id": 3092,
    "pet_type": 1,
    "expand_pet": [],
    "level": 60
  },
  {
    "_row_key": 33,
    "_row_size": 17,
    "id": 3095,
    "pet_type": 1,
    "expand_pet": [],
    "level": 60
  },
  {
    "_row_key": 34,
    "_row_size": 17,
    "id": 3100,
    "pet_type": 1,
    "expand_pet": [],
    "level": 60
  },
  {
    "_row_key": 35,
    "_row_size": 17,
    "id": 3102,
    "pet_type": 1,
    "expand_pet": [],
    "level": 60
  },
  {
    "_row_key": 36,
    "_row_size": 17,
    "id": 3105,
    "pet_type": 1,
    "expand_pet": [],
    "level": 60
  },
  {
    "_row_key": 37,
    "_row_size": 17,
    "id": 3108,
    "pet_type": 1,
    "expand_pet": [],
    "level": 60
  },
  {
    "_row_key": 38,
    "_row_size": 17,
    "id": 3111,
    "pet_type": 1,
    "expand_pet": [],
    "level": 60
  },
  {
    "_row_key": 39,
    "_row_size": 17,
    "id": 3114,
    "pet_type": 1,
    "expand_pet": [],
    "level": 60
  },
  {
    "_row_key": 40,
    "_row_size": 17,
    "id": 3117,
    "pet_type": 2,
    "expand_pet": [],
    "level": 60
  },
  {
    "_row_key": 41,
    "_row_size": 17,
    "id": 3120,
    "pet_type": 2,
    "expand_pet": [],
    "level": 60
  },
  {
    "_row_key": 42,
    "_row_size": 17,
    "id": 3123,
    "pet_type": 1,
    "expand_pet": [],
    "level": 60
  },
  {
    "_row_key": 43,
    "_row_size": 17,
    "id": 3126,
    "pet_type": 2,
    "expand_pet": [],
    "level": 60
  },
  {
    "_row_key": 44,
    "_row_size": 17,
    "id": 3129,
    "pet_type": 1,
    "expand_pet": [],
    "level": 60
  },
  {
    "_row_key": 45,
    "_row_size": 17,
    "id": 3132,
    "pet_type": 1,
    "expand_pet": [],
    "level": 60
  },
  {
    "_row_key": 46,
    "_row_size": 17,
    "id": 3138,
    "pet_type": 1,
    "expand_pet": [],
    "level": 60
  },
  {
    "_row_key": 47,
    "_row_size": 17,
    "id": 3141,
    "pet_type": 1,
    "expand_pet": [],
    "level": 60
  },
  {
    "_row_key": 48,
    "_row_size": 17,
    "id": 3144,
    "pet_type": 1,
    "expand_pet": [],
    "level": 60
  },
  {
    "_row_key": 49,
    "_row_size": 17,
    "id": 3147,
    "pet_type": 1,
    "expand_pet": [],
    "level": 60
  },
  {
    "_row_key": 50,
    "_row_size": 17,
    "id": 3150,
    "pet_type": 1,
    "expand_pet": [],
    "level": 60
  },
  {
    "_row_key": 51,
    "_row_size": 17,
    "id": 3153,
    "pet_type": 1,
    "expand_pet": [],
    "level": 60
  },
  {
    "_row_key": 52,
    "_row_size": 17,
    "id": 3156,
    "pet_type": 1,
    "expand_pet": [],
    "level": 60
  },
  {
    "_row_key": 53,
    "_row_size": 17,
    "id": 3157,
    "pet_type": 1,
    "expand_pet": [],
    "level": 60
  },
  {
    "_row_key": 54,
    "_row_size": 17,
    "id": 3167,
    "pet_type": 1,
    "expand_pet": [],
    "level": 60
  },
  {
    "_row_key": 55,
    "_row_size": 17,
    "id": 3171,
    "pet_type": 1,
    "expand_pet": [],
    "level": 60
  },
  {
    "_row_key": 56,
    "_row_size": 17,
    "id": 3174,
    "pet_type": 1,
    "expand_pet": [],
    "level": 60
  },
  {
    "_row_key": 57,
    "_row_size": 17,
    "id": 3177,
    "pet_type": 1,
    "expand_pet": [],
    "level": 60
  },
  {
    "_row_key": 58,
    "_row_size": 17,
    "id": 3182,
    "pet_type": 1,
    "expand_pet": [],
    "level": 60
  },
  {
    "_row_key": 59,
    "_row_size": 17,
    "id": 3189,
    "pet_type": 1,
    "expand_pet": [],
    "level": 60
  },
  {
    "_row_key": 60,
    "_row_size": 17,
    "id": 3192,
    "pet_type": 1,
    "expand_pet": [],
    "level": 60
  },
  {
    "_row_key": 61,
    "_row_size": 17,
    "id": 3194,
    "pet_type": 2,
    "expand_pet": [],
    "level": 60
  },
  {
    "_row_key": 62,
    "_row_size": 17,
    "id": 3197,
    "pet_type": 2,
    "expand_pet": [],
    "level": 60
  },
  {
    "_row_key": 63,
    "_row_size": 17,
    "id": 3199,
    "pet_type": 2,
    "expand_pet": [],
    "level": 60
  },
  {
    "_row_key": 64,
    "_row_size": 17,
    "id": 3202,
    "pet_type": 1,
    "expand_pet": [],
    "level": 60
  },
  {
    "_row_key": 65,
    "_row_size": 17,
    "id": 3210,
    "pet_type": 1,
    "expand_pet": [],
    "level": 60
  },
  {
    "_row_key": 66,
    "_row_size": 17,
    "id": 3216,
    "pet_type": 1,
    "expand_pet": [],
    "level": 60
  },
  {
    "_row_key": 67,
    "_row_size": 17,
    "id": 3226,
    "pet_type": 1,
    "expand_pet": [],
    "level": 60
  },
  {
    "_row_key": 68,
    "_row_size": 17,
    "id": 3227,
    "pet_type": 2,
    "expand_pet": [],
    "level": 60
  },
  {
    "_row_key": 69,
    "_row_size": 17,
    "id": 3241,
    "pet_type": 1,
    "expand_pet": [],
    "level": 60
  },
  {
    "_row_key": 70,
    "_row_size": 17,
    "id": 3246,
    "pet_type": 1,
    "expand_pet": [],
    "level": 60
  },
  {
    "_row_key": 71,
    "_row_size": 17,
    "id": 3252,
    "pet_type": 1,
    "expand_pet": [],
    "level": 60
  },
  {
    "_row_key": 72,
    "_row_size": 17,
    "id": 3259,
    "pet_type": 1,
    "expand_pet": [],
    "level": 60
  },
  {
    "_row_key": 73,
    "_row_size": 17,
    "id": 3263,
    "pet_type": 1,
    "expand_pet": [],
    "level": 60
  },
  {
    "_row_key": 74,
    "_row_size": 17,
    "id": 3267,
    "pet_type": 2,
    "expand_pet": [],
    "level": 60
  },
  {
    "_row_key": 75,
    "_row_size": 17,
    "id": 3269,
    "pet_type": 1,
    "expand_pet": [],
    "level": 60
  },
  {
    "_row_key": 76,
    "_row_size": 17,
    "id": 3278,
    "pet_type": 1,
    "expand_pet": [],
    "level": 60
  },
  {
    "_row_key": 77,
    "_row_size": 17,
    "id": 3285,
    "pet_type": 1,
    "expand_pet": [],
    "level": 60
  },
  {
    "_row_key": 78,
    "_row_size": 17,
    "id": 3286,
    "pet_type": 1,
    "expand_pet": [],
    "level": 60
  },
  {
    "_row_key": 79,
    "_row_size": 17,
    "id": 3287,
    "pet_type": 1,
    "expand_pet": [],
    "level": 60
  },
  {
    "_row_key": 80,
    "_row_size": 17,
    "id": 3295,
    "pet_type": 1,
    "expand_pet": [],
    "level": 60
  },
  {
    "_row_key": 81,
    "_row_size": 17,
    "id": 3296,
    "pet_type": 1,
    "expand_pet": [],
    "level": 60
  },
  {
    "_row_key": 82,
    "_row_size": 17,
    "id": 3303,
    "pet_type": 1,
    "expand_pet": [],
    "level": 60
  },
  {
    "_row_key": 83,
    "_row_size": 17,
    "id": 3304,
    "pet_type": 1,
    "expand_pet": [],
    "level": 60
  },
  {
    "_row_key": 84,
    "_row_size": 17,
    "id": 3305,
    "pet_type": 1,
    "expand_pet": [],
    "level": 60
  },
  {
    "_row_key": 85,
    "_row_size": 17,
    "id": 3308,
    "pet_type": 1,
    "expand_pet": [],
    "level": 60
  },
  {
    "_row_key": 86,
    "_row_size": 17,
    "id": 3311,
    "pet_type": 1,
    "expand_pet": [],
    "level": 60
  },
  {
    "_row_key": 87,
    "_row_size": 17,
    "id": 3317,
    "pet_type": 1,
    "expand_pet": [],
    "level": 60
  },
  {
    "_row_key": 88,
    "_row_size": 17,
    "id": 3320,
    "pet_type": 2,
    "expand_pet": [],
    "level": 60
  },
  {
    "_row_key": 89,
    "_row_size": 17,
    "id": 3332,
    "pet_type": 1,
    "expand_pet": [],
    "level": 60
  },
  {
    "_row_key": 90,
    "_row_size": 17,
    "id": 3335,
    "pet_type": 1,
    "expand_pet": [],
    "level": 60
  },
  {
    "_row_key": 91,
    "_row_size": 17,
    "id": 3346,
    "pet_type": 1,
    "expand_pet": [],
    "level": 60
  },
  {
    "_row_key": 92,
    "_row_size": 17,
    "id": 3350,
    "pet_type": 2,
    "expand_pet": [],
    "level": 60
  },
  {
    "_row_key": 93,
    "_row_size": 17,
    "id": 3359,
    "pet_type": 1,
    "expand_pet": [],
    "level": 60
  },
  {
    "_row_key": 94,
    "_row_size": 17,
    "id": 3368,
    "pet_type": 2,
    "expand_pet": [],
    "level": 60
  },
  {
    "_row_key": 95,
    "_row_size": 17,
    "id": 3375,
    "pet_type": 1,
    "expand_pet": [],
    "level": 60
  },
  {
    "_row_key": 96,
    "_row_size": 17,
    "id": 3377,
    "pet_type": 2,
    "expand_pet": [],
    "level": 60
  },
  {
    "_row_key": 97,
    "_row_size": 17,
    "id": 3380,
    "pet_type": 1,
    "expand_pet": [],
    "level": 60
  },
  {
    "_row_key": 98,
    "_row_size": 17,
    "id": 3381,
    "pet_type": 2,
    "expand_pet": [],
    "level": 60
  },
  {
    "_row_key": 99,
    "_row_size": 17,
    "id": 3383,
    "pet_type": 2,
    "expand_pet": [],
    "level": 60
  },
  {
    "_row_key": 100,
    "_row_size": 17,
    "id": 3386,
    "pet_type": 2,
    "expand_pet": [],
    "level": 60
  },
  {
    "_row_key": 101,
    "_row_size": 17,
    "id": 3397,
    "pet_type": 1,
    "expand_pet": [],
    "level": 60
  },
  {
    "_row_key": 102,
    "_row_size": 17,
    "id": 3400,
    "pet_type": 1,
    "expand_pet": [],
    "level": 60
  },
  {
    "_row_key": 103,
    "_row_size": 17,
    "id": 3405,
    "pet_type": 2,
    "expand_pet": [],
    "level": 60
  },
  {
    "_row_key": 104,
    "_row_size": 17,
    "id": 3407,
    "pet_type": 1,
    "expand_pet": [],
    "level": 60
  },
  {
    "_row_key": 105,
    "_row_size": 17,
    "id": 3411,
    "pet_type": 1,
    "expand_pet": [],
    "level": 60
  },
  {
    "_row_key": 106,
    "_row_size": 17,
    "id": 3412,
    "pet_type": 2,
    "expand_pet": [],
    "level": 60
  },
  {
    "_row_key": 107,
    "_row_size": 17,
    "id": 3420,
    "pet_type": 1,
    "expand_pet": [],
    "level": 60
  },
  {
    "_row_key": 108,
    "_row_size": 17,
    "id": 3430,
    "pet_type": 2,
    "expand_pet": [],
    "level": 60
  },
  {
    "_row_key": 109,
    "_row_size": 17,
    "id": 3431,
    "pet_type": 2,
    "expand_pet": [],
    "level": 60
  },
  {
    "_row_key": 110,
    "_row_size": 17,
    "id": 3432,
    "pet_type": 2,
    "expand_pet": [],
    "level": 60
  },
  {
    "_row_key": 111,
    "_row_size": 17,
    "id": 3433,
    "pet_type": 2,
    "expand_pet": [],
    "level": 60
  },
  {
    "_row_key": 112,
    "_row_size": 17,
    "id": 3437,
    "pet_type": 1,
    "expand_pet": [],
    "level": 60
  },
  {
    "_row_key": 113,
    "_row_size": 17,
    "id": 3439,
    "pet_type": 2,
    "expand_pet": [],
    "level": 60
  },
  {
    "_row_key": 114,
    "_row_size": 17,
    "id": 3443,
    "pet_type": 2,
    "expand_pet": [],
    "level": 60
  },
  {
    "_row_key": 115,
    "_row_size": 17,
    "id": 3444,
    "pet_type": 1,
    "expand_pet": [],
    "level": 60
  },
  {
    "_row_key": 116,
    "_row_size": 17,
    "id": 3448,
    "pet_type": 1,
    "expand_pet": [],
    "level": 60
  },
  {
    "_row_key": 117,
    "_row_size": 17,
    "id": 3449,
    "pet_type": 1,
    "expand_pet": [],
    "level": 60
  },
  {
    "_row_key": 118,
    "_row_size": 17,
    "id": 3450,
    "pet_type": 1,
    "expand_pet": [],
    "level": 60
  },
  {
    "_row_key": 119,
    "_row_size": 17,
    "id": 3451,
    "pet_type": 1,
    "expand_pet": [],
    "level": 60
  },
  {
    "_row_key": 120,
    "_row_size": 17,
    "id": 3456,
    "pet_type": 1,
    "expand_pet": [],
    "level": 60
  },
  {
    "_row_key": 121,
    "_row_size": 17,
    "id": 3458,
    "pet_type": 2,
    "expand_pet": [],
    "level": 60
  },
  {
    "_row_key": 122,
    "_row_size": 17,
    "id": 3459,
    "pet_type": 2,
    "expand_pet": [],
    "level": 60
  },
  {
    "_row_key": 123,
    "_row_size": 17,
    "id": 3460,
    "pet_type": 2,
    "expand_pet": [],
    "level": 60
  },
  {
    "_row_key": 124,
    "_row_size": 17,
    "id": 3461,
    "pet_type": 2,
    "expand_pet": [],
    "level": 60
  },
  {
    "_row_key": 125,
    "_row_size": 17,
    "id": 3462,
    "pet_type": 2,
    "expand_pet": [],
    "level": 60
  },
  {
    "_row_key": 126,
    "_row_size": 17,
    "id": 3463,
    "pet_type": 2,
    "expand_pet": [],
    "level": 60
  },
  {
    "_row_key": 127,
    "_row_size": 17,
    "id": 3464,
    "pet_type": 2,
    "expand_pet": [],
    "level": 60
  },
  {
    "_row_key": 128,
    "_row_size": 17,
    "id": 3465,
    "pet_type": 2,
    "expand_pet": [],
    "level": 60
  },
  {
    "_row_key": 129,
    "_row_size": 17,
    "id": 3469,
    "pet_type": 1,
    "expand_pet": [],
    "level": 60
  },
  {
    "_row_key": 130,
    "_row_size": 17,
    "id": 3470,
    "pet_type": 1,
    "expand_pet": [],
    "level": 60
  },
  {
    "_row_key": 131,
    "_row_size": 17,
    "id": 3471,
    "pet_type": 1,
    "expand_pet": [],
    "level": 60
  },
  {
    "_row_key": 132,
    "_row_size": 17,
    "id": 3472,
    "pet_type": 1,
    "expand_pet": [],
    "level": 60
  },
  {
    "_row_key": 133,
    "_row_size": 17,
    "id": 3477,
    "pet_type": 1,
    "expand_pet": [],
    "level": 60
  },
  {
    "_row_key": 134,
    "_row_size": 17,
    "id": 3482,
    "pet_type": 2,
    "expand_pet": [],
    "level": 60
  },
  {
    "_row_key": 135,
    "_row_size": 17,
    "id": 3485,
    "pet_type": 2,
    "expand_pet": [],
    "level": 60
  },
  {
    "_row_key": 136,
    "_row_size": 17,
    "id": 3486,
    "pet_type": 1,
    "expand_pet": [],
    "level": 60
  },
  {
    "_row_key": 137,
    "_row_size": 17,
    "id": 3491,
    "pet_type": 1,
    "expand_pet": [],
    "level": 60
  },
  {
    "_row_key": 138,
    "_row_size": 17,
    "id": 3492,
    "pet_type": 1,
    "expand_pet": [],
    "level": 60
  },
  {
    "_row_key": 139,
    "_row_size": 17,
    "id": 3498,
    "pet_type": 2,
    "expand_pet": [],
    "level": 60
  },
  {
    "_row_key": 140,
    "_row_size": 17,
    "id": 3499,
    "pet_type": 1,
    "expand_pet": [],
    "level": 60
  },
  {
    "_row_key": 141,
    "_row_size": 17,
    "id": 3502,
    "pet_type": 1,
    "expand_pet": [],
    "level": 60
  },
  {
    "_row_key": 142,
    "_row_size": 17,
    "id": 3507,
    "pet_type": 1,
    "expand_pet": [],
    "level": 60
  },
  {
    "_row_key": 143,
    "_row_size": 17,
    "id": 3510,
    "pet_type": 1,
    "expand_pet": [],
    "level": 60
  },
  {
    "_row_key": 144,
    "_row_size": 17,
    "id": 3518,
    "pet_type": 2,
    "expand_pet": [],
    "level": 60
  },
  {
    "_row_key": 145,
    "_row_size": 17,
    "id": 3521,
    "pet_type": 1,
    "expand_pet": [],
    "level": 60
  },
  {
    "_row_key": 146,
    "_row_size": 17,
    "id": 3526,
    "pet_type": 2,
    "expand_pet": [],
    "level": 60
  },
  {
    "_row_key": 147,
    "_row_size": 17,
    "id": 3527,
    "pet_type": 2,
    "expand_pet": [],
    "level": 60
  },
  {
    "_row_key": 148,
    "_row_size": 17,
    "id": 3528,
    "pet_type": 1,
    "expand_pet": [],
    "level": 60
  },
  {
    "_row_key": 149,
    "_row_size": 17,
    "id": 3530,
    "pet_type": 1,
    "expand_pet": [],
    "level": 60
  },
  {
    "_row_key": 150,
    "_row_size": 17,
    "id": 3535,
    "pet_type": 1,
    "expand_pet": [],
    "level": 60
  },
  {
    "_row_key": 151,
    "_row_size": 17,
    "id": 3538,
    "pet_type": 1,
    "expand_pet": [],
    "level": 60
  },
  {
    "_row_key": 152,
    "_row_size": 17,
    "id": 3541,
    "pet_type": 1,
    "expand_pet": [],
    "level": 60
  },
  {
    "_row_key": 153,
    "_row_size": 17,
    "id": 3546,
    "pet_type": 1,
    "expand_pet": [],
    "level": 60
  },
  {
    "_row_key": 154,
    "_row_size": 17,
    "id": 3547,
    "pet_type": 1,
    "expand_pet": [],
    "level": 60
  },
  {
    "_row_key": 155,
    "_row_size": 17,
    "id": 3551,
    "pet_type": 1,
    "expand_pet": [],
    "level": 60
  },
  {
    "_row_key": 156,
    "_row_size": 17,
    "id": 3552,
    "pet_type": 1,
    "expand_pet": [],
    "level": 60
  },
  {
    "_row_key": 157,
    "_row_size": 17,
    "id": 3553,
    "pet_type": 1,
    "expand_pet": [],
    "level": 60
  },
  {
    "_row_key": 158,
    "_row_size": 17,
    "id": 3554,
    "pet_type": 1,
    "expand_pet": [],
    "level": 60
  },
  {
    "_row_key": 159,
    "_row_size": 17,
    "id": 3556,
    "pet_type": 1,
    "expand_pet": [],
    "level": 60
  },
  {
    "_row_key": 160,
    "_row_size": 17,
    "id": 3557,
    "pet_type": 1,
    "expand_pet": [],
    "level": 60
  },
  {
    "_row_key": 161,
    "_row_size": 17,
    "id": 3558,
    "pet_type": 1,
    "expand_pet": [],
    "level": 60
  },
  {
    "_row_key": 162,
    "_row_size": 17,
    "id": 3559,
    "pet_type": 1,
    "expand_pet": [],
    "level": 60
  },
  {
    "_row_key": 163,
    "_row_size": 17,
    "id": 3569,
    "pet_type": 2,
    "expand_pet": [],
    "level": 60
  },
  {
    "_row_key": 164,
    "_row_size": 17,
    "id": 3571,
    "pet_type": 1,
    "expand_pet": [],
    "level": 60
  },
  {
    "_row_key": 165,
    "_row_size": 17,
    "id": 3583,
    "pet_type": 1,
    "expand_pet": [],
    "level": 60
  },
  {
    "_row_key": 166,
    "_row_size": 17,
    "id": 3585,
    "pet_type": 1,
    "expand_pet": [],
    "level": 60
  },
  {
    "_row_key": 167,
    "_row_size": 17,
    "id": 3604,
    "pet_type": 1,
    "expand_pet": [],
    "level": 60
  },
  {
    "_row_key": 168,
    "_row_size": 17,
    "id": 3605,
    "pet_type": 1,
    "expand_pet": [],
    "level": 60
  },
  {
    "_row_key": 169,
    "_row_size": 17,
    "id": 3608,
    "pet_type": 2,
    "expand_pet": [],
    "level": 60
  },
  {
    "_row_key": 170,
    "_row_size": 17,
    "id": 3609,
    "pet_type": 1,
    "expand_pet": [],
    "level": 60
  },
  {
    "_row_key": 171,
    "_row_size": 17,
    "id": 3612,
    "pet_type": 1,
    "expand_pet": [],
    "level": 60
  },
  {
    "_row_key": 172,
    "_row_size": 17,
    "id": 3613,
    "pet_type": 1,
    "expand_pet": [],
    "level": 60
  },
  {
    "_row_key": 173,
    "_row_size": 17,
    "id": 3615,
    "pet_type": 1,
    "expand_pet": [],
    "level": 60
  },
  {
    "_row_key": 174,
    "_row_size": 17,
    "id": 3619,
    "pet_type": 1,
    "expand_pet": [],
    "level": 60
  }
]