[
  {
    "_row_key": 1,
    "_row_size": 33,
    "id": 1500001,
    "topic": "星光对决",
    "start_time": "2026-01-26 04:00:00",
    "period": "7 00:00:00",
    "challenge_id": [
      1002
    ],
    "type": [
      4
    ],
    "star_rewards": [
      {
        "magic_level": 42,
        "star_required": [
          496,
          22016,
          22272,
          22528
        ],
        "reward": [
          752,
          22784,
          23040,
          23296
        ],
        "photo_reward": [
          1008,
          23552,
          23808,
          24064
        ]
      }
    ],
    "show_reward": [
      {
        "item_type": 48,
        "item_id": 49,
        "item_count": 50
      }
    ]
  },
  {
    "_row_key": 2,
    "_row_size": 33,
    "id": 1500002,
    "topic": "星光对决",
    "start_time": "2026-02-02 04:00:00",
    "period": "7 00:00:00",
    "challenge_id": [
      1000
    ],
    "type": [
      3
    ],
    "star_rewards": [
      {
        "magic_level": 42,
        "star_required": [
          496,
          22016,
          22272,
          25856
        ],
        "reward": [
          752,
          22784,
          23040,
          26112
        ],
        "photo_reward": [
          1008,
          23552,
          23808,
          26368
        ]
      }
    ],
    "show_reward": [
      {
        "item_type": 48,
        "item_id": 49,
        "item_count": 50
      }
    ]
  },
  {
    "_row_key": 3,
    "_row_size": 33,
    "id": 1500003,
    "topic": "星光对决",
    "start_time": "2026-02-09 04:00:00",
    "period": "7 00:00:00",
    "challenge_id": [
      1005
    ],
    "type": [
      14
    ],
    "star_rewards": [
      {
        "magic_level": 42,
        "star_required": [
          496,
          22016,
          22272,
          27136
        ],
        "reward": [
          752,
          22784,
          23040,
          27392
        ],
        "photo_reward": [
          1008,
          23552,
          23808,
          27648
        ]
      }
    ],
    "show_reward": [
      {
        "item_type": 48,
        "item_id": 49,
        "item_count": 50
      }
    ]
  },
  {
    "_row_key": 4,
    "_row_size": 33,
    "id": 1500004,
    "topic": "星光对决",
    "start_time": "2026-02-16 04:00:00",
    "period": "7 00:00:00",
    "challenge_id": [
      1001
    ],
    "type": [
      3
    ],
    "star_rewards": [
      {
        "magic_level": 42,
        "star_required": [
          496,
          22016,
          22272,
          28416
        ],
        "reward": [
          752,
          22784,
          23040,
          28672
        ],
        "photo_reward": [
          1008,
          23552,
          23808,
          28928
        ]
      }
    ],
    "show_reward": [
      {
        "item_type": 48,
        "item_id": 49,
        "item_count": 50
      }
    ]
  },
  {
    "_row_key": 5,
    "_row_size": 33,
    "id": 1500005,
    "topic": "星光对决",
    "start_time": "2026-02-23 04:00:00",
    "period": "7 00:00:00",
    "challenge_id": [
      1007
    ],
    "type": [
      14
    ],
    "star_rewards": [
      {
        "magic_level": 42,
        "star_required": [
          496,
          22016,
          22272,
          29696
        ],
        "reward": [
          752,
          22784,
          23040,
          29952
        ],
        "photo_reward": [
          1008,
          23552,
          23808,
          30208
        ]
      }
    ],
    "show_reward": [
      {
        "item_type": 48,
        "item_id": 49,
        "item_count": 50
      }
    ]
  },
  {
    "_row_key": 6,
    "_row_size": 33,
    "id": 1500006,
    "topic": "星光对决",
    "start_time": "2026-03-02 04:00:00",
    "period": "7 00:00:00",
    "challenge_id": [
      1003
    ],
    "type": [
      18,
      19
    ],
    "star_rewards": [
      {
        "magic_level": 42,
        "star_required": [
          496,
          22016,
          22272,
          30976
        ],
        "reward": [
          752,
          22784,
          23040,
          31232
        ],
        "photo_reward": [
          1008,
          23552,
          23808,
          31488
        ]
      }
    ],
    "show_reward": [
      {
        "item_type": 48,
        "item_id": 49,
        "item_count": 50
      }
    ]
  },
  {
    "_row_key": 7,
    "_row_size": 33,
    "id": 1500007,
    "topic": "星光对决",
    "start_time": "2026-03-09 04:00:00",
    "period": "7 00:00:00",
    "challenge_id": [
      1006
    ],
    "type": [
      18,
      8
    ],
    "star_rewards": [
      {
        "magic_level": 42,
        "star_required": [
          496,
          22016,
          22272,
          32256
        ],
        "reward": [
          752,
          22784,
          23040,
          32512
        ],
        "photo_reward": [
          1008,
          23552,
          23808,
          32768
        ]
      }
    ],
    "show_reward": [
      {
        "item_type": 48,
        "item_id": 49,
        "item_count": 50
      }
    ]
  },
  {
    "_row_key": 8,
    "_row_size": 33,
    "id": 1500008,
    "topic": "星光对决",
    "start_time": "2026-03-16 04:00:00",
    "period": "7 00:00:00",
    "challenge_id": [
      1004
    ],
    "type": [
      19,
      9
    ],
    "star_rewards": [
      {
        "magic_level": 42,
        "star_required": [
          496,
          22016,
          22272,
          33536
        ],
        "reward": [
          752,
          22784,
          23040,
          33792
        ],
        "photo_reward": [
          1008,
          23552,
          23808,
          34048
        ]
      }
    ],
    "show_reward": [
      {
        "item_type": 48,
        "item_id": 49,
        "item_count": 50
      }
    ]
  },
  {
    "_row_key": 9,
    "_row_size": 33,
    "id": 1500101,
    "topic": "星光对决",
    "start_time": "2026-03-23 04:00:00",
    "period": "7 00:00:00",
    "challenge_id": [
      1002
    ],
    "type": [
      4
    ],
    "star_rewards": [
      {
        "magic_level": 42,
        "star_required": [
          496,
          22016,
          22272,
          22528
        ],
        "reward": [
          752,
          22784,
          23040,
          23296
        ],
        "photo_reward": [
          1008,
          23552,
          23808,
          24064
        ]
      }
    ],
    "show_reward": [
      {
        "item_type": 48,
        "item_id": 49,
        "item_count": 50
      }
    ]
  },
  {
    "_row_key": 10,
    "_row_size": 33,
    "id": 1500102,
    "topic": "星光对决",
    "start_time": "2026-03-30 04:00:00",
    "period": "7 00:00:00",
    "challenge_id": [
      1000
    ],
    "type": [
      3
    ],
    "star_rewards": [
      {
        "magic_level": 42,
        "star_required": [
          496,
          22016,
          22272,
          25856
        ],
        "reward": [
          752,
          22784,
          23040,
          26112
        ],
        "photo_reward": [
          1008,
          23552,
          23808,
          26368
        ]
      }
    ],
    "show_reward": [
      {
        "item_type": 48,
        "item_id": 49,
        "item_count": 50
      }
    ]
  },
  {
    "_row_key": 11,
    "_row_size": 33,
    "id": 1500103,
    "topic": "星光对决",
    "start_time": "2026-04-06 04:00:00",
    "period": "7 00:00:00",
    "challenge_id": [
      1005
    ],
    "type": [
      14
    ],
    "star_rewards": [
      {
        "magic_level": 42,
        "star_required": [
          496,
          22016,
          22272,
          27136
        ],
        "reward": [
          752,
          22784,
          23040,
          27392
        ],
        "photo_reward": [
          1008,
          23552,
          23808,
          27648
        ]
      }
    ],
    "show_reward": [
      {
        "item_type": 48,
        "item_id": 49,
        "item_count": 50
      }
    ]
  },
  {
    "_row_key": 12,
    "_row_size": 33,
    "id": 1500104,
    "topic": "星光对决",
    "start_time": "2026-04-13 04:00:00",
    "period": "7 00:00:00",
    "challenge_id": [
      1001
    ],
    "type": [
      3
    ],
    "star_rewards": [
      {
        "magic_level": 42,
        "star_required": [
          496,
          22016,
          22272,
          28416
        ],
        "reward": [
          752,
          22784,
          23040,
          28672
        ],
        "photo_reward": [
          1008,
          23552,
          23808,
          28928
        ]
      }
    ],
    "show_reward": [
      {
        "item_type": 48,
        "item_id": 49,
        "item_count": 50
      }
    ]
  },
  {
    "_row_key": 13,
    "_row_size": 33,
    "id": 1500105,
    "topic": "星光对决",
    "start_time": "2026-04-20 04:00:00",
    "period": "7 00:00:00",
    "challenge_id": [
      1007
    ],
    "type": [
      14
    ],
    "star_rewards": [
      {
        "magic_level": 42,
        "star_required": [
          496,
          22016,
          22272,
          29696
        ],
        "reward": [
          752,
          22784,
          23040,
          29952
        ],
        "photo_reward": [
          1008,
          23552,
          23808,
          30208
        ]
      }
    ],
    "show_reward": [
      {
        "item_type": 48,
        "item_id": 49,
        "item_count": 50
      }
    ]
  },
  {
    "_row_key": 14,
    "_row_size": 33,
    "id": 1500106,
    "topic": "星光对决",
    "start_time": "2026-04-27 04:00:00",
    "period": "7 00:00:00",
    "challenge_id": [
      1003
    ],
    "type": [
      18,
      19
    ],
    "star_rewards": [
      {
        "magic_level": 42,
        "star_required": [
          496,
          22016,
          22272,
          30976
        ],
        "reward": [
          752,
          22784,
          23040,
          31232
        ],
        "photo_reward": [
          1008,
          23552,
          23808,
          31488
        ]
      }
    ],
    "show_reward": [
      {
        "item_type": 48,
        "item_id": 49,
        "item_count": 50
      }
    ]
  },
  {
    "_row_key": 15,
    "_row_size": 33,
    "id": 1500107,
    "topic": "星光对决",
    "start_time": "2026-05-04 04:00:00",
    "period": "7 00:00:00",
    "challenge_id": [
      1006
    ],
    "type": [
      18,
      8
    ],
    "star_rewards": [
      {
        "magic_level": 42,
        "star_required": [
          496,
          22016,
          22272,
          32256
        ],
        "reward": [
          752,
          22784,
          23040,
          32512
        ],
        "photo_reward": [
          1008,
          23552,
          23808,
          32768
        ]
      }
    ],
    "show_reward": [
      {
        "item_type": 48,
        "item_id": 49,
        "item_count": 50
      }
    ]
  },
  {
    "_row_key": 16,
    "_row_size": 33,
    "id": 1500108,
    "topic": "星光对决",
    "start_time": "2026-05-11 04:00:00",
    "period": "7 00:00:00",
    "challenge_id": [
      1004
    ],
    "type": [
      19,
      9
    ],
    "star_rewards": [
      {
        "magic_level": 42,
        "star_required": [
          496,
          22016,
          22272,
          33536
        ],
        "reward": [
          752,
          22784,
          23040,
          33792
        ],
        "photo_reward": [
          1008,
          23552,
          23808,
          34048
        ]
      }
    ],
    "show_reward": [
      {
        "item_type": 48,
        "item_id": 49,
        "item_count": 50
      }
    ]
  }
]